funcversion/__init__.py
funcversion/core.py
funcversion/exceptions.py
funcversion/py.typed
funcversion/version.py
funcversion-0.1.32.dist-info/LICENSE
funcversion-0.1.32.dist-info/METADATA
funcversion-0.1.32.dist-info/WHEEL
funcversion-0.1.32.dist-info/RECORD
