Metadata-Version: 2.1
Name: funcversion
Version: 0.1.32
Summary: A Python library for managing multiple versions of functions using decorators.
License: MIT
Author: Pizzaface
Requires-Python: >=3.11,<4.0
Classifier: License :: OSI Approved :: MIT License
Classifier: Programming Language :: Python :: 3
Classifier: Programming Language :: Python :: 3.11
Classifier: Programming Language :: Python :: 3.12
Classifier: Programming Language :: Python :: 3.13
Requires-Dist: packaging (>=24.2,<25.0)
